pr0cks_extension/__init__.py
pr0cks_extension/cli.py
pr0cks_extension-0.1.0.dist-info/LICENSE
pr0cks_extension-0.1.0.dist-info/WHEEL
pr0cks_extension-0.1.0.dist-info/METADATA
pr0cks_extension-0.1.0.dist-info/RECORD
