Metadata-Version: 2.1
Name: pr0cks-extension
Version: 0.1.0
Summary: Basis for CLI extensions for pr0cks
Home-page: https://gitlab.com/NamingThingsIsHard/net/pr0cks/pr0cks-extension
License: GPL-3.0-or-later
Keywords: transparent proxy,extension,plugin
Author: LoveIsGrief
Author-email: loveisgrief@tuta.io
Requires-Python: >=3.6,<4.0
Classifier: Development Status :: 3 - Alpha
Classifier: Environment :: Plugins
Classifier: License :: OSI Approved :: GNU General Public License v3 or later (GPLv3+)
Classifier: Operating System :: POSIX
Classifier: Programming Language :: Python :: 3
Classifier: Programming Language :: Python :: 3.6
Classifier: Programming Language :: Python :: 3.7
Classifier: Programming Language :: Python :: 3.8
Classifier: Topic :: System :: Networking
Project-URL: Bug Tracker, https://gitlab.com/NamingThingsIsHard/net/pr0cks/pr0cks-extension
Project-URL: Repository, https://gitlab.com/NamingThingsIsHard/net/pr0cks/pr0cks-extension
